ace_cm/.DS_Store
ace_cm/__init__.py
ace_cm/build/asset-manifest.json
ace_cm/build/index.html
ace_cm/build/static/js/2.422ca0c4.chunk.js
ace_cm/build/static/js/2.422ca0c4.chunk.js.LICENSE.txt
ace_cm/build/static/js/2.422ca0c4.chunk.js.map
ace_cm/build/static/js/main.666d1b34.chunk.js
ace_cm/build/static/js/main.666d1b34.chunk.js.map
ace_cm/build/static/js/runtime-main.9b51049f.js
ace_cm/build/static/js/runtime-main.9b51049f.js.map
ace_cm/cm.py
ace_cm/ecm.py
ace_cm/package-lock.json
ace_cm/package.json
ace_cm/public/index.html
ace_cm/src/index.ts
ace_cm/src/react-app-env.d.ts
ace_cm/tsconfig.json
ace_cm-0.0.8.dist-info/METADATA
ace_cm-0.0.8.dist-info/WHEEL
ace_cm-0.0.8.dist-info/RECORD
