Metadata-Version: 2.3
Name: ace-cm
Version: 0.0.8
Summary: Access and save cookies from Streamlit for Streamlit
License: Apache-2.0
Author: Cem Bakar
Author-email: cem.bakar@sonova.com
Requires-Python: >=3.10,<4.0
Classifier: License :: OSI Approved :: Apache Software License
Classifier: Programming Language :: Python :: 3
Classifier: Programming Language :: Python :: 3.10
Classifier: Programming Language :: Python :: 3.11
Classifier: Programming Language :: Python :: 3.12
Classifier: Programming Language :: Python :: 3.13
Requires-Dist: cryptography (>=41.0.3)
Requires-Dist: msal (>=1.31.0)
Requires-Dist: streamlit (>=1.39)
